LICENSE.txt
README.md
setup.cfg
setup.py
ct_finance/__init__.py
ct_finance/ct_display.py
ct_finance/ct_io.py
ct_finance.egg-info/PKG-INFO
ct_finance.egg-info/SOURCES.txt
ct_finance.egg-info/dependency_links.txt
ct_finance.egg-info/requires.txt
ct_finance.egg-info/top_level.txt
ct_finance/data/__init__.py
ct_finance/data/classify.py
ct_finance/data/data.py
ct_finance/data/dir_utils.py
ct_finance/db_structure/__init__.py
ct_finance/db_structure/data_db.py
ct_finance/db_structure/display_db.py
ct_finance/docopt_util/__init__.py
ct_finance/docopt_util/docopt_utility.py